spyderDergiPark/__init__.py
spyderDergiPark/createTopicLinkDict.py
spyderDergiPark/spyderDergiPark.py
spyderDergiPark-0.0.9.dist-info/LICENCE
spyderDergiPark-0.0.9.dist-info/METADATA
spyderDergiPark-0.0.9.dist-info/WHEEL
spyderDergiPark-0.0.9.dist-info/top_level.txt
spyderDergiPark-0.0.9.dist-info/RECORD
