Metadata-Version: 2.1
Name: spyderDergiPark
Version: 0.0.9
Summary: A Python library that enables downloading articles from DergiPark (https://dergipark.org.tr) related to a topic or a search phrase.
Home-page: https://github.com/senaerdogan/spyderDergiPark
Author: Sena Erdogan
Author-email: saadetsenaerdogan@gmail.com
License: UNKNOWN
Project-URL: Bug Tracker, https://github.com/senaerdogan/spyderDergiPark/issues
Platform: UNKNOWN
Classifier: Programming Language :: Python :: 3
Classifier: License :: OSI Approved :: MIT License
Classifier: Operating System :: OS Independent
Requires-Python: >=3.6
License-File: LICENCE
